DynamicNestedField/DjangoModelsFields.py
DynamicNestedField/DynamicNestedField.py
DynamicNestedField/__init__.py
DynamicNestedField-0.0.16.dist-info/LICENSE.txt
DynamicNestedField-0.0.16.dist-info/METADATA
DynamicNestedField-0.0.16.dist-info/WHEEL
DynamicNestedField-0.0.16.dist-info/top_level.txt
DynamicNestedField-0.0.16.dist-info/RECORD
