Metadata-Version: 2.1
Name: DynamicNestedField
Version: 0.0.16
Summary: DynamicNestedField is a set of tools used to perform dynamic nested operation on django models.
Home-page: https://github.com/NAMEER242/DynamicNestedField
Author: Nameer Haider
Author-email: nmeer5242@gmail.com
Project-URL: Bug Tracker, https://github.com/NAMEER242/DynamicNestedField/issues
Project-URL: repository, https://github.com/NAMEER242/DynamicNestedField
Classifier: Programming Language :: Python :: 3
Classifier: License :: OSI Approved :: MIT License
Classifier: Operating System :: OS Independent
Classifier: Development Status :: 4 - Beta
Classifier: Framework :: Django
Requires-Python: >=3.9
License-File: LICENSE.txt
Requires-Dist: setuptools >=42
Requires-Dist: asgiref >=3.5.2
Requires-Dist: Django >=4.1.3
Requires-Dist: djangorestframework >=3.14.0
Requires-Dist: pytz >=2022.6
Requires-Dist: sqlparse >=0.4.3
Requires-Dist: tzdata >=2022.6
Requires-Dist: django-restql ==0.15.3
Requires-Dist: django-filter ==22.1
